{
  "screenTitle": "Hikes Search",
  "search": {
    "placeholder": "Find my hike..."
  },
  "favorites": {
    "title": "Favorites",
    "empty": "No favorites yet. Long press on a hike to add it."
  },
  "list": {
    "allHikes": "All Hikes",
    "searchResults": "Search Results",
    "noResults": "No results found",
    "noHikes": "No hikes available",
    "premium": "Premium"
  },
  "detail": {
    "distance": "Distance",
    "roundtrip": "Roundtrip",
    "skippedSections": "Skipped Sections",
    "mapAvailable": "map available",
    "mapsAvailable": "maps available",
    "startHike": "Select this hike",
    "error": "Unable to load hike details"
  }
}
